{"trial_id": "14", "hyperparameters": {"space": [{"class_name": "Int", "config": {"name": "number_of_layers", "default": null, "conditions": [], "min_value": 1, "max_value": 5, "step": 1, "sampling": "linear"}}, {"class_name": "Choice", "config": {"name": "learning_rate", "default": 0.1, "conditions": [], "values": [0.1, 0.01, 0.001, 0.0001], "ordered": true}}], "values": {"number_of_layers": 2, "learning_rate": 0.0001}}, "metrics": {"metrics": {"loss": {"direction": "min", "observations": [{"value": [1.2254968484242756], "step": 49}]}, "accuracy": {"direction": "max", "observations": [{"value": [0.454096257686615], "step": 49}]}, "val_loss": {"direction": "min", "observations": [{"value": [1.1100565195083618], "step": 49}]}, "val_accuracy": {"direction": "max", "observations": [{"value": [0.5244865616162618], "step": 49}]}}}, "score": 0.5244865616162618, "best_step": 49, "status": "COMPLETED", "message": null}