{"trial_id": "36", "hyperparameters": {"space": [{"class_name": "Int", "config": {"name": "number_of_layers", "default": null, "conditions": [], "min_value": 1, "max_value": 3, "step": 1, "sampling": "linear"}}, {"class_name": "Choice", "config": {"name": "learning_rate", "default": 0.001, "conditions": [], "values": [0.001, 0.0001], "ordered": true}}, {"class_name": "Int", "config": {"name": "nodes_layer_1", "default": null, "conditions": [], "min_value": 30, "max_value": 50, "step": 10, "sampling": "linear"}}, {"class_name": "Int", "config": {"name": "nodes_layer_2", "default": null, "conditions": [], "min_value": 30, "max_value": 50, "step": 10, "sampling": "linear"}}, {"class_name": "Int", "config": {"name": "nodes_layer_3", "default": null, "conditions": [], "min_value": 30, "max_value": 50, "step": 10, "sampling": "linear"}}], "values": {"number_of_layers": 2, "learning_rate": 0.001, "nodes_layer_1": 30, "nodes_layer_2": 30, "nodes_layer_3": 40}}, "metrics": {"metrics": {"loss": {"direction": "min", "observations": [{"value": [1.3374266624450684], "step": 161}]}, "accuracy": {"direction": "max", "observations": [{"value": [0.704489529132843], "step": 161}]}, "val_loss": {"direction": "min", "observations": [{"value": [0.9395667910575867], "step": 161}]}, "val_accuracy": {"direction": "max", "observations": [{"value": [0.6830466985702515], "step": 161}]}}}, "score": 0.6830466985702515, "best_step": 161, "status": "COMPLETED", "message": null}